Metadata-Version: 1.1
Name: misago-social-auth-app-django
Version: 2.1.0
Summary: Python Social Authentication, Django integration (Misago fork).
Home-page: https://github.com/rafalp/misago-social-app-django
Author: Matias Aguirre, Rafał Pitoń
Author-email: rafio.xudb@gmail.com
License: BSD
Keywords: django,social auth
Platform: UNKNOWN
Classifier: Development Status :: 4 - Beta
Classifier: Topic :: Internet
Classifier: License :: OSI Approved :: BSD License
Classifier: Intended Audience :: Developers
Classifier: Environment :: Web Environment
Classifier: Programming Language :: Python
Classifier: Programming Language :: Python :: 2.7
Classifier: Programming Language :: Python :: 3
